coloors/__init__.py
coloors/bcolors.py
coloors-1.0.0.dist-info/METADATA
coloors-1.0.0.dist-info/WHEEL
coloors-1.0.0.dist-info/licenses/LICENSE
coloors-1.0.0.dist-info/RECORD
