Metadata-Version: 2.4
Name: coloors
Version: 1.0.0
Summary: Simple Python package to print & show colored text in the terminal.
Project-URL: Homepage, https://github.com/Ouassim-Hamdani/coloors
Project-URL: Issues, https://github.com/Ouassim-Hamdani/coloors
Author-email: Ouassim Hamdani <o_hamdani@estin.dz>
License-File: LICENSE
Classifier: License :: OSI Approved :: GNU General Public License v3 (GPLv3)
Classifier: Operating System :: OS Independent
Classifier: Programming Language :: Python :: 3
Requires-Python: >=3.0
